app/__init__.py
app/main.py
gyb_classification_model/__init__.py
gyb_classification_model/predictor.py
gyb_classification_model-0.1.10.dist-info/licenses/LICENSE
models/MedicalReportClassifierV10.pkl
models/MedicalReportLabelMapV10.pkl
models/MedicalReportVectorizerV10.pkl
models/OnlyDeliverSlipPharmOrderModelV4.pkl
models/OnlyDeliverSlipPharmOrderVectorizerV4.pkl
models/OnlyDeliverSlipPharmOrderlabel_mapV4.pkl
models/label_mapV31.pkl
models/textClassificationModelV31.pkl
models/vectorizerV31.pkl
gyb_classification_model-0.1.10.dist-info/METADATA
gyb_classification_model-0.1.10.dist-info/WHEEL
gyb_classification_model-0.1.10.dist-info/top_level.txt
gyb_classification_model-0.1.10.dist-info/RECORD
