Metadata-Version: 2.4
Name: gyb-classification-model
Version: 0.1.10
Summary: ML classification models package
Home-page: https://github.com/GreenBills/GYB-Classification-Model
Author: Hrutik-M
Author-email: hrutik.m@codearray.tech
Requires-Python: >=3.10
License-File: LICENSE
Requires-Dist: pandas==2.2.3
Requires-Dist: scikit-learn==1.6.1
Requires-Dist: seaborn==0.13.2
Requires-Dist: nltk==3.9.1
Requires-Dist: xgboost==3.0.0
Dynamic: author
Dynamic: author-email
Dynamic: description
Dynamic: description-content-type
Dynamic: home-page
Dynamic: license-file
Dynamic: requires-dist
Dynamic: requires-python
Dynamic: summary
